py2sambvca/__init__.py
py2sambvca/py2sambvca.py
py2sambvca/radii_tables/__init__.py
py2sambvca/radii_tables/default.py
py2sambvca/radii_tables/format_table.py
py2sambvca/radii_tables/vanDerWaals.py
py2sambvca-2.0.0.post1.dist-info/licenses/LICENSE
py2sambvca-2.0.0.post1.dist-info/METADATA
py2sambvca-2.0.0.post1.dist-info/WHEEL
py2sambvca-2.0.0.post1.dist-info/top_level.txt
py2sambvca-2.0.0.post1.dist-info/RECORD
