Metadata-Version: 2.4
Name: py2sambvca
Version: 2.0.0.post1
Summary: Simple thin client to interface python scripts with SambVca catalytic pocket Fortran calculator.
Home-page: https://github.com/JacksonBurns/py2sambvca
Author: Jackson Burns
License: GNU GPLv3
Classifier: Programming Language :: Python :: 3.6
Classifier: Programming Language :: Python :: 3.7
Classifier: Programming Language :: Python :: 3.8
Classifier: Programming Language :: Python :: 3.9
Classifier: Programming Language :: Python :: 3.10
Classifier: Programming Language :: Python :: 3.11
Classifier: Programming Language :: Python :: 3.12
Classifier: Programming Language :: Python :: 3.13
Requires-Python: >=3.6
License-File: LICENSE
Dynamic: author
Dynamic: classifier
Dynamic: description
Dynamic: description-content-type
Dynamic: home-page
Dynamic: license
Dynamic: license-file
Dynamic: requires-python
Dynamic: summary
